{
  "openapi": "3.0.1",
  "info": {
    "title": "task11_api",
    "version": "2024-08-18T17:27:24Z"
  },
  "servers": [
    {
      "url": "https://r7289r6138.execute-api.eu-central-1.amazonaws.com/{basePath}",
      "variables": {
        "basePath": {
          "default": "api"
        }
      }
    }
  ],
  "paths": {
    "/reservations": {
      "get": {
        "summary": "Get Reservations",
        "description": "Retrieve a list of reservations",
        "responses": {
          "200": {
            "description": "200 response",
            "content": {
              "application/json": {
                "schema": {
                  "$ref": "#/components/schemas/Empty"
                }
              }
            }
          }
        },
        "security": [
          {
            "authorizer": []
          }
        ],
        "x-amazon-apigateway-integration": {
          "httpMethod": "POST",
          "uri": "arn:aws:apigateway:eu-central-1:lambda:path/2015-03-31/functions/arn:aws:lambda:eu-central-1:196241772369:function:api_handler/invocations",
          "responses": {
            "default": {
              "statusCode": "200"
            }
          },
          "passthroughBehavior": "when_no_match",
          "type": "aws_proxy"
        }
      },
      "post": {
        "summary": "Create Reservation",
        "description": "Create a new reservation",
        "requestBody": {
          "description": "Reservation details",
          "content": {
            "application/json": {
              "schema": {
                "$ref": "#/components/schemas/Empty"
              }
            }
          },
          "required": true
        },
        "responses": {
          "200": {
            "description": "200 response",
            "content": {
              "application/json": {
                "schema": {
                  "$ref": "#/components/schemas/Empty"
                }
              }
            }
          }
        },
        "security": [
          {
            "authorizer": []
          }
        ],
        "x-amazon-apigateway-integration": {
          "httpMethod": "POST",
          "uri": "arn:aws:apigateway:eu-central-1:lambda:path/2015-03-31/functions/arn:aws:lambda:eu-central-1:196241772369:function:api_handler/invocations",
          "responses": {
            "default": {
              "statusCode": "200"
            }
          },
          "passthroughBehavior": "when_no_match",
          "type": "aws_proxy"
        }
      }
    },
    "/tables": {
      "get": {
        "summary": "Get Tables",
        "description": "Retrieve a list of tables",
        "responses": {
          "200": {
            "description": "200 response",
            "content": {
              "application/json": {
                "schema": {
                  "$ref": "#/components/schemas/Empty"
                }
              }
            }
          }
        },
        "security": [
          {
            "authorizer": []
          }
        ],
        "x-amazon-apigateway-integration": {
          "httpMethod": "POST",
          "uri": "arn:aws:apigateway:eu-central-1:lambda:path/2015-03-31/functions/arn:aws:lambda:eu-central-1:196241772369:function:api_handler/invocations",
          "responses": {
            "default": {
              "statusCode": "200"
            }
          },
          "passthroughBehavior": "when_no_match",
          "type": "aws_proxy"
        }
      },
      "post": {
        "summary": "Create Table",
        "description": "Create a new table",
        "requestBody": {
          "description": "Table details",
          "content": {
            "application/json": {
              "schema": {
                "$ref": "#/components/schemas/Empty"
              }
            }
          },
          "required": true
        },
        "responses": {
          "200": {
            "description": "200 response",
            "content": {
              "application/json": {
                "schema": {
                  "$ref": "#/components/schemas/Empty"
                }
              }
            }
          }
        },
        "security": [
          {
            "authorizer": []
          }
        ],
        "x-amazon-apigateway-integration": {
          "httpMethod": "POST",
          "uri": "arn:aws:apigateway:eu-central-1:lambda:path/2015-03-31/functions/arn:aws:lambda:eu-central-1:196241772369:function:api_handler/invocations",
          "responses": {
            "default": {
              "statusCode": "200"
            }
          },
          "passthroughBehavior": "when_no_match",
          "type": "aws_proxy"
        }
      }
    },
    "/signin": {
      "post": {
        "summary": "User Signin",
        "description": "Authenticate a user",
        "requestBody": {
          "description": "Signin credentials",
          "content": {
            "application/json": {
              "schema": {
                "$ref": "#/components/schemas/Empty"
              }
            }
          },
          "required": true
        },
        "responses": {
          "200": {
            "description": "200 response",
            "content": {
              "application/json": {
                "schema": {
                  "$ref": "#/components/schemas/Empty"
                }
              }
            }
          }
        },
        "x-amazon-apigateway-integration": {
          "httpMethod": "POST",
          "uri": "arn:aws:apigateway:eu-central-1:lambda:path/2015-03-31/functions/arn:aws:lambda:eu-central-1:196241772369:function:api_handler/invocations",
          "responses": {
            "default": {
              "statusCode": "200"
            }
          },
          "passthroughBehavior": "when_no_match",
          "type": "aws_proxy"
        }
      }
    },
    "/signup": {
      "post": {
        "summary": "User Signup",
        "description": "Register a new user",
        "requestBody": {
          "description": "Signup details",
          "content": {
            "application/json": {
              "schema": {
                "$ref": "#/components/schemas/Empty"
              }
            }
          },
          "required": true
        },
        "responses": {
          "200": {
            "description": "200 response",
            "content": {
              "application/json": {
                "schema": {
                  "$ref": "#/components/schemas/Empty"
                }
              }
            }
          }
        },
        "x-amazon-apigateway-integration": {
          "httpMethod": "POST",
          "uri": "arn:aws:apigateway:eu-central-1:lambda:path/2015-03-31/functions/arn:aws:lambda:eu-central-1:196241772369:function:api_handler/invocations",
          "responses": {
            "default": {
              "statusCode": "200"
            }
          },
          "passthroughBehavior": "when_no_match",
          "type": "aws_proxy"
        }
      }
    },
    "/tables/{tableId}": {
      "get": {
        "summary": "Get Table by ID",
        "description": "Retrieve table details by ID",
        "parameters": [
          {
            "name": "tableId",
            "in": "path",
            "required": true,
            "schema": {
              "type": "string"
            }
          }
        ],
        "responses": {
          "200": {
            "description": "200 response",
            "content": {
              "application/json": {
                "schema": {
                  "$ref": "#/components/schemas/Empty"
                }
              }
            }
          }
        },
        "security": [
          {
            "authorizer": []
          }
        ],
        "x-amazon-apigateway-integration": {
          "httpMethod": "POST",
          "uri": "arn:aws:apigateway:eu-central-1:lambda:path/2015-03-31/functions/arn:aws:lambda:eu-central-1:196241772369:function:api_handler/invocations",
          "responses": {
            "default": {
              "statusCode": "200"
            }
          },
          "passthroughBehavior": "when_no_match",
          "type": "aws_proxy"
        }
      }
    }
  },
  "components": {
    "schemas": {
      "Empty": {
        "title": "Empty Schema",
        "type": "object"
      }
    },
    "securitySchemes": {
      "authorizer": {
        "type": "apiKey",
        "name": "Authorization",
        "in": "header",
        "x-amazon-apigateway-authtype": "cognito_user_pools",
        "x-amazon-apigateway-authorizer": {
          "x-syndicate-cognito-userpool-names": ["${booking_userpool}"],
          "type": "cognito_user_pools"
        }
      }
    }
  }
}
